redsentinel/__init__.py
redsentinel/ai_summary.py
redsentinel/cli.py
redsentinel/doctor.py
redsentinel/menu.py
redsentinel/assets/redsentinel-logo.png
redsentinel/core/__init__.py
redsentinel/core/advisor.py
redsentinel/core/ai_client.py
redsentinel/core/ai_interpreter.py
redsentinel/core/ai_summary.py
redsentinel/core/analyzer.py
redsentinel/core/compliance_map.py
redsentinel/core/cvss.py
redsentinel/core/exploit_engine.py
redsentinel/core/external_tools.py
redsentinel/core/html_reporter.py
redsentinel/core/json_exporter.py
redsentinel/core/normalizer.py
redsentinel/core/pdf_reporter.py
redsentinel/core/planner.py
redsentinel/core/reporter.py
redsentinel/core/risk.py
redsentinel/core/risk_heatmap.py
redsentinel/core/simulator.py
redsentinel/core/state.py
redsentinel/core/tools_runner.py
redsentinel/core/utils.py
redsentinel/reports/karl.com_report.json
redsentinel/reports/karlseyra.xyz_report.json
redsentinel/reports/report_karl_com.html
redsentinel/reports/report_karl_com.pdf
redsentinel/reports/report_karlseyra_xyz.html
redsentinel/reports/report_karlseyra_xyz.pdf
redsentinel/reports/risk_heatmap.png
redsentinel/samples/nikto.txt
redsentinel/scanners/nikto_scan.py
redsentinel/scanners/nmap_scan.py
redsentinel/scanners/runner.py
redsentinel/scanners/whatweb_scan.py
redsentinel/templates/report.html
redsentinel/utils/tools.py
redsentinel-0.1.0.dist-info/licenses/LICENSE
redsentinel-0.1.0.dist-info/METADATA
redsentinel-0.1.0.dist-info/WHEEL
redsentinel-0.1.0.dist-info/entry_points.txt
redsentinel-0.1.0.dist-info/top_level.txt
redsentinel-0.1.0.dist-info/RECORD
