Metadata-Version: 2.4
Name: redsentinel
Version: 0.1.0
Summary: RedSentinel – AI-Assisted Security Assessment Tool
Author: Hackura
License: MIT
Classifier: Development Status :: 3 - Alpha
Classifier: Intended Audience :: Information Technology
Classifier: Topic :: Security
Classifier: License :: OSI Approved :: MIT License
Classifier: Programming Language :: Python :: 3
Classifier: Operating System :: POSIX
Requires-Python: >=3.10
License-File: LICENSE
Requires-Dist: requests>=2.31.0
Requires-Dist: jinja2>=3.1.2
Requires-Dist: python-dotenv>=1.0.0
Requires-Dist: rich>=13.7.0
Provides-Extra: visuals
Requires-Dist: matplotlib>=3.8.0; extra == "visuals"
Requires-Dist: numpy>=1.26.0; extra == "visuals"
Provides-Extra: reports
Requires-Dist: weasyprint>=60.0; extra == "reports"
Provides-Extra: all
Requires-Dist: matplotlib>=3.8.0; extra == "all"
Requires-Dist: numpy>=1.26.0; extra == "all"
Requires-Dist: weasyprint>=60.0; extra == "all"
Dynamic: license-file
